<?xml version="1.0" encoding="utf-8"?>
<?xml-stylesheet type="text/xsl" href="REP_RA.xsl"?>
<ACTIVITY_ENROL>
    <company_id>A</company_id>
    <dsts_control_number>A</dsts_control_number>
    <enrolment_version>1.23</enrolment_version>
    <date_saved>1999-01-21</date_saved>
    <application_type>APPROVED</application_type>
    <software_version>string</software_version>
    <data_checksum>string</data_checksum>
    <dossier_id_prefix>HC6-024-</dossier_id_prefix>
    <dossier_id>A</dossier_id>
    <reg_activity_lead>UNASSIGNED</reg_activity_lead>
    <reg_activity_type>SNDS</reg_activity_type>
    <fee_class>string by default</fee_class>
    <not_lasa>Y</not_lasa>
    <reason_filing>A</reason_filing>
    <related_activity>
        <reg_activity_type>VDIN</reg_activity_type>
        <date_cleared>1999-01-21</date_cleared>
        <control_number>000000</control_number>
        <dossier_id>A</dossier_id>
        <manufacturer_name>A</manufacturer_name>
        <reason_filing>A</reason_filing>
        <assoc_dins>
            <din_number>00000000</din_number>
            <din_number>00000001</din_number>
            <din_number>00000002</din_number>
			<din_number>00000003</din_number>
            <din_number>00000004</din_number>
            <din_number>00000005</din_number>
        </assoc_dins>
    </related_activity>
    <related_activity>
        <reg_activity_type>VDIN</reg_activity_type>
        <date_cleared>1999-01-21</date_cleared>
        <control_number>000000</control_number>
        <dossier_id>A</dossier_id>
        <manufacturer_name>A</manufacturer_name>
        <reason_filing>A</reason_filing>
        <assoc_dins>
            <din_number>00000000</din_number>
            <din_number>00000000</din_number>
            <din_number>00000000</din_number>
        </assoc_dins>
    </related_activity>
    <related_activity>
        <reg_activity_type>VDIN</reg_activity_type>
        <date_cleared>1999-01-21</date_cleared>
        <control_number>000000</control_number>
        <dossier_id>A</dossier_id>
        <manufacturer_name>A</manufacturer_name>
        <reason_filing>A</reason_filing>
        <assoc_dins>
            <din_number>00000000</din_number>
            <din_number>00000000</din_number>
            <din_number>00000000</din_number>
        </assoc_dins>
    </related_activity>
    <is_third_party>Y</is_third_party>
    <notifiable_change_types>
        <text_label_change>Y</text_label_change>
        <drug_substance_change>Y</drug_substance_change>
        <formulation_change>Y</formulation_change>
        <specification_change>Y</specification_change>
        <expiry_storage_change>Y</expiry_storage_change>
        <manufact_method_change>Y</manufact_method_change>
        <manufact_site_change>Y</manufact_site_change>
        <container_size_change>Y</container_size_change>
        <packaging_spec_change>Y</packaging_spec_change>
        <packaging_materials_change>Y</packaging_materials_change>
        <other_change>Y</other_change>
		<other_change_details>A</other_change_details>
    </notifiable_change_types>
    <rationale_types>
        <new_roa>Y</new_roa>
        <new_claims>Y</new_claims>
        <change_formulation>Y</change_formulation>
        <change_drug_substance>Y</change_drug_substance>
        <replace_sterility>Y</replace_sterility>
        <confirmitory_studies>Y</confirmitory_studies>
        <other_rationale>Y</other_rationale>
        <other_rationale_details>A</other_rationale_details>
    </rationale_types>
    <contact_record>
        <amend_record>Y</amend_record>
        <rep_contact_role>PRIMARY</rep_contact_role>
        <rep_contact_details>
            <salutation>DR</salutation>
            <given_name>A</given_name>
            <initials>A</initials>
            <surname>A</surname>
            <job_title>A</job_title>
            <language_correspondance>fr</language_correspondance>
            <phone_num>A</phone_num>
            <phone_ext>A</phone_ext>
            <fax_num>A</fax_num>
            <email>A</email>
        </rep_contact_details>
    </contact_record>
    <contact_record>
        <amend_record>Y</amend_record>
        <rep_contact_role>SECONDARY</rep_contact_role>
        <rep_contact_details>
            <salutation>DR</salutation>
            <given_name>A</given_name>
            <initials>A</initials>
            <surname>A</surname>
            <job_title>A</job_title>
            <language_correspondance>fr</language_correspondance>
            <phone_num>A</phone_num>
            <phone_ext>A</phone_ext>
            <fax_num>A</fax_num>
            <email>A</email>
        </rep_contact_details>
    </contact_record>
</ACTIVITY_ENROL>